acsploit/__init__.py
acsploit/__main__.py
acsploit/exploits/__init__.py
acsploit/exploits/bombs/__init__.py
acsploit/exploits/bombs/compression/__init__.py
acsploit/exploits/bombs/compression/gz.py
acsploit/exploits/bombs/compression/pdf.py
acsploit/exploits/bombs/compression/tar_gz.py
acsploit/exploits/bombs/compression/zip.py
acsploit/exploits/bombs/fork/__init__.py
acsploit/exploits/bombs/fork/fork_bombs.py
acsploit/exploits/bombs/git/__init__.py
acsploit/exploits/bombs/git/git_bombs.py
acsploit/exploits/bombs/images/__init__.py
acsploit/exploits/bombs/images/deflate.py
acsploit/exploits/bombs/images/jpeg_bad_header.py
acsploit/exploits/bombs/images/jpeg_bomb.py
acsploit/exploits/bombs/images/png.py
acsploit/exploits/bombs/xml/__init__.py
acsploit/exploits/bombs/xml/billion_laughs.py
acsploit/exploits/geometry/__init__.py
acsploit/exploits/geometry/convex_hull.py
acsploit/exploits/graphs/__init__.py
acsploit/exploits/graphs/min_span_tree/__init__.py
acsploit/exploits/graphs/min_span_tree/kruskal.py
acsploit/exploits/hashes/__init__.py
acsploit/exploits/hashes/collisions/__init__.py
acsploit/exploits/hashes/collisions/adler32.py
acsploit/exploits/hashes/collisions/bsd.py
acsploit/exploits/hashes/collisions/chicken_scheme.py
acsploit/exploits/hashes/collisions/crc32.py
acsploit/exploits/hashes/collisions/custom_hash.py
acsploit/exploits/hashes/collisions/fletcher.py
acsploit/exploits/hashes/collisions/java.py
acsploit/exploits/hashes/collisions/java7_hashmap.py
acsploit/exploits/hashes/collisions/java8+_hashmap.py
acsploit/exploits/hashes/collisions/java_common.py
acsploit/exploits/hashes/collisions/java_fast.py
acsploit/exploits/hashes/collisions/java_z3.py
acsploit/exploits/hashes/collisions/lrc.py
acsploit/exploits/hashes/collisions/php5.py
acsploit/exploits/hashes/collisions/php5_common.py
acsploit/exploits/hashes/collisions/php5_fast.py
acsploit/exploits/hashes/collisions/python2_32.py
acsploit/exploits/hashes/collisions/sum.py
acsploit-1.0.0.dist-info/LICENSE
acsploit-1.0.0.dist-info/METADATA
acsploit-1.0.0.dist-info/WHEEL
acsploit-1.0.0.dist-info/entry_points.txt
acsploit-1.0.0.dist-info/top_level.txt
acsploit-1.0.0.dist-info/RECORD
