Metadata-Version: 2.1
Name: acsploit
Version: 1.0.0
Summary: A tool for generating worst-case inputs for algorithms
Home-page: https://github.com/twosixlabs/acsploit
Author: Two Six Technologies
License: UNKNOWN
Platform: UNKNOWN
Requires-Python: >=3.5, <4
License-File: LICENSE
Requires-Dist: colorama
Requires-Dist: cmd2
Requires-Dist: delayed-assert
Requires-Dist: exrex
Requires-Dist: graphviz
Requires-Dist: more-itertools
Requires-Dist: netifaces
Requires-Dist: pdoc3
Requires-Dist: ply
Requires-Dist: pypng
Requires-Dist: pytest-cov
Requires-Dist: pytest-xdist
Requires-Dist: python-utils
Requires-Dist: requests
Requires-Dist: scapy
Requires-Dist: scipy
Requires-Dist: tqdm
Requires-Dist: z3-solver
